<annotation>
	<folder>Chips</folder>
	<filename>IMG7.jpg</filename>
	<path>D:\Computer vision\Grocery dataset\Chips\IMG7.jpg</path>
	<source>
		<database>Unknown</database>
	</source>
	<size>
		<width>3264</width>
		<height>2448</height>
		<depth>3</depth>
	</size>
	<segmented>0</segmented>
	<object>
		<name>chip</name>
		<pose>Unspecified</pose>
		<truncated>0</truncated>
		<difficult>0</difficult>
		<bndbox>
			<xmin>25</xmin>
			<ymin>308</ymin>
			<xmax>664</xmax>
			<ymax>1216</ymax>
		</bndbox>
	</object>
	<object>
		<name>chip</name>
		<pose>Unspecified</pose>
		<truncated>0</truncated>
		<difficult>0</difficult>
		<bndbox>
			<xmin>566</xmin>
			<ymin>247</ymin>
			<xmax>1287</xmax>
			<ymax>1201</ymax>
		</bndbox>
	</object>
	<object>
		<name>chip</name>
		<pose>Unspecified</pose>
		<truncated>0</truncated>
		<difficult>0</difficult>
		<bndbox>
			<xmin>1287</xmin>
			<ymin>288</ymin>
			<xmax>1831</xmax>
			<ymax>1208</ymax>
		</bndbox>
	</object>
	<object>
		<name>chip</name>
		<pose>Unspecified</pose>
		<truncated>0</truncated>
		<difficult>0</difficult>
		<bndbox>
			<xmin>1828</xmin>
			<ymin>347</ymin>
			<xmax>2451</xmax>
			<ymax>1193</ymax>
		</bndbox>
	</object>
	<object>
		<name>chip</name>
		<pose>Unspecified</pose>
		<truncated>0</truncated>
		<difficult>0</difficult>
		<bndbox>
			<xmin>2400</xmin>
			<ymin>411</ymin>
			<xmax>3000</xmax>
			<ymax>1219</ymax>
		</bndbox>
	</object>
	<object>
		<name>chip</name>
		<pose>Unspecified</pose>
		<truncated>0</truncated>
		<difficult>0</difficult>
		<bndbox>
			<xmin>1784</xmin>
			<ymin>1519</ymin>
			<xmax>2374</xmax>
			<ymax>2362</ymax>
		</bndbox>
	</object>
	<object>
		<name>chip</name>
		<pose>Unspecified</pose>
		<truncated>0</truncated>
		<difficult>0</difficult>
		<bndbox>
			<xmin>1231</xmin>
			<ymin>1454</ymin>
			<xmax>1738</xmax>
			<ymax>2342</ymax>
		</bndbox>
	</object>
	<object>
		<name>chip</name>
		<pose>Unspecified</pose>
		<truncated>0</truncated>
		<difficult>0</difficult>
		<bndbox>
			<xmin>831</xmin>
			<ymin>1511</ymin>
			<xmax>1215</xmax>
			<ymax>2326</ymax>
		</bndbox>
	</object>
	<object>
		<name>chip</name>
		<pose>Unspecified</pose>
		<truncated>0</truncated>
		<difficult>0</difficult>
		<bndbox>
			<xmin>246</xmin>
			<ymin>1603</ymin>
			<xmax>905</xmax>
			<ymax>2337</ymax>
		</bndbox>
	</object>
	<object>
		<name>chip</name>
		<pose>Unspecified</pose>
		<truncated>0</truncated>
		<difficult>0</difficult>
		<bndbox>
			<xmin>2359</xmin>
			<ymin>1531</ymin>
			<xmax>2836</xmax>
			<ymax>2362</ymax>
		</bndbox>
	</object>
	<object>
		<name>chip</name>
		<pose>Unspecified</pose>
		<truncated>1</truncated>
		<difficult>0</difficult>
		<bndbox>
			<xmin>2764</xmin>
			<ymin>1519</ymin>
			<xmax>3264</xmax>
			<ymax>2337</ymax>
		</bndbox>
	</object>
	<object>
		<name>chip</name>
		<pose>Unspecified</pose>
		<truncated>0</truncated>
		<difficult>0</difficult>
		<bndbox>
			<xmin>1279</xmin>
			<ymin>298</ymin>
			<xmax>1825</xmax>
			<ymax>1237</ymax>
		</bndbox>
	</object>
</annotation>
