<annotation>
	<folder>Sodas</folder>
	<filename>IMG_0598.JPEG</filename>
	<path>/Users/birajpoudyal/Desktop/biraj/Sodas/IMG_0598.JPEG</path>
	<source>
		<database>Unknown</database>
	</source>
	<size>
		<width>1536</width>
		<height>2048</height>
		<depth>3</depth>
	</size>
	<segmented>0</segmented>
	<object>
		<name>squirt soda</name>
		<pose>Unspecified</pose>
		<truncated>0</truncated>
		<difficult>0</difficult>
		<bndbox>
			<xmin>752</xmin>
			<ymin>169</ymin>
			<xmax>922</xmax>
			<ymax>919</ymax>
		</bndbox>
	</object>
	<object>
		<name>squirt soda</name>
		<pose>Unspecified</pose>
		<truncated>0</truncated>
		<difficult>0</difficult>
		<bndbox>
			<xmin>957</xmin>
			<ymin>164</ymin>
			<xmax>1164</xmax>
			<ymax>984</ymax>
		</bndbox>
	</object>
	<object>
		<name>squirt soda</name>
		<pose>Unspecified</pose>
		<truncated>0</truncated>
		<difficult>0</difficult>
		<bndbox>
			<xmin>1222</xmin>
			<ymin>181</ymin>
			<xmax>1222</xmax>
			<ymax>184</ymax>
		</bndbox>
	</object>
	<object>
		<name>squirt soda</name>
		<pose>Unspecified</pose>
		<truncated>0</truncated>
		<difficult>0</difficult>
		<bndbox>
			<xmin>1222</xmin>
			<ymin>191</ymin>
			<xmax>1479</xmax>
			<ymax>1076</ymax>
		</bndbox>
	</object>
	<object>
		<name>coke soda</name>
		<pose>Unspecified</pose>
		<truncated>0</truncated>
		<difficult>0</difficult>
		<bndbox>
			<xmin>77</xmin>
			<ymin>104</ymin>
			<xmax>344</xmax>
			<ymax>741</ymax>
		</bndbox>
	</object>
	<object>
		<name>coke soda</name>
		<pose>Unspecified</pose>
		<truncated>0</truncated>
		<difficult>0</difficult>
		<bndbox>
			<xmin>54</xmin>
			<ymin>754</ymin>
			<xmax>297</xmax>
			<ymax>1209</ymax>
		</bndbox>
	</object>
	<object>
		<name>coke soda</name>
		<pose>Unspecified</pose>
		<truncated>0</truncated>
		<difficult>0</difficult>
		<bndbox>
			<xmin>327</xmin>
			<ymin>861</ymin>
			<xmax>402</xmax>
			<ymax>1259</ymax>
		</bndbox>
	</object>
	<object>
		<name>coke soda</name>
		<pose>Unspecified</pose>
		<truncated>0</truncated>
		<difficult>0</difficult>
		<bndbox>
			<xmin>417</xmin>
			<ymin>916</ymin>
			<xmax>514</xmax>
			<ymax>1346</ymax>
		</bndbox>
	</object>
	<object>
		<name>coke soda</name>
		<pose>Unspecified</pose>
		<truncated>0</truncated>
		<difficult>0</difficult>
		<bndbox>
			<xmin>542</xmin>
			<ymin>964</ymin>
			<xmax>664</xmax>
			<ymax>1466</ymax>
		</bndbox>
	</object>
	<object>
		<name>coke soda</name>
		<pose>Unspecified</pose>
		<truncated>0</truncated>
		<difficult>0</difficult>
		<bndbox>
			<xmin>699</xmin>
			<ymin>1046</ymin>
			<xmax>849</xmax>
			<ymax>1536</ymax>
		</bndbox>
	</object>
	<object>
		<name>sprite soda</name>
		<pose>Unspecified</pose>
		<truncated>0</truncated>
		<difficult>0</difficult>
		<bndbox>
			<xmin>142</xmin>
			<ymin>1229</ymin>
			<xmax>247</xmax>
			<ymax>1464</ymax>
		</bndbox>
	</object>
	<object>
		<name>sprite soda</name>
		<pose>Unspecified</pose>
		<truncated>0</truncated>
		<difficult>0</difficult>
		<bndbox>
			<xmin>272</xmin>
			<ymin>1314</ymin>
			<xmax>464</xmax>
			<ymax>1624</ymax>
		</bndbox>
	</object>
	<object>
		<name>canada dry soda</name>
		<pose>Unspecified</pose>
		<truncated>0</truncated>
		<difficult>0</difficult>
		<bndbox>
			<xmin>487</xmin>
			<ymin>1486</ymin>
			<xmax>634</xmax>
			<ymax>1759</ymax>
		</bndbox>
	</object>
	<object>
		<name>RC soda</name>
		<pose>Unspecified</pose>
		<truncated>0</truncated>
		<difficult>0</difficult>
		<bndbox>
			<xmin>984</xmin>
			<ymin>1204</ymin>
			<xmax>1307</xmax>
			<ymax>1824</ymax>
		</bndbox>
	</object>
	<object>
		<name>AW soda</name>
		<pose>Unspecified</pose>
		<truncated>0</truncated>
		<difficult>0</difficult>
		<bndbox>
			<xmin>1367</xmin>
			<ymin>1451</ymin>
			<xmax>1454</xmax>
			<ymax>2006</ymax>
		</bndbox>
	</object>
</annotation>
